rss2pdf/__init__.py
rss2pdf/__main__.py
rss2pdf/config.toml
rss2pdf-0.1.1.dist-info/LICENSE
rss2pdf-0.1.1.dist-info/METADATA
rss2pdf-0.1.1.dist-info/WHEEL
rss2pdf-0.1.1.dist-info/top_level.txt
rss2pdf-0.1.1.dist-info/RECORD
