Metadata-Version: 2.1
Name: rss2pdf
Version: 0.1.1
Author-email: Jochem Hölscher <a.fake@e.mail>
Project-URL: homepage, https://github.com/JJJHolscher/rss2pdf
Classifier: Programming Language :: Python :: 3
Classifier: License :: OSI Approved :: MIT License
Classifier: Operating System :: OS Independent
Requires-Python: >=3.11
License-File: LICENSE
Requires-Dist: feedparser
Requires-Dist: pypdf
Requires-Dist: pdfkit
Requires-Dist: argtoml
